README.md
linkml_activitypub/__init__.py
linkml_activitypub/_version.py
linkml_activitypub/activitypub.py
linkml_activitypub/activitypub.yaml
linkml_activitypub/activitystreams.py
linkml_activitypub/activitystreams.yaml
linkml_activitypub/dataclass/__init__.py
linkml_activitypub/dataclass/activitypub.py
linkml_activitypub/dataclass/activitystreams.py
linkml_activitypub-0.2.0.dist-info/LICENSE
linkml_activitypub-0.2.0.dist-info/METADATA
linkml_activitypub-0.2.0.dist-info/WHEEL
linkml_activitypub-0.2.0.dist-info/RECORD
