Metadata-Version: 2.1
Name: linkml-activitypub
Version: 0.2.0
Summary: LinkML representation of ActivityStreams Schema
License: GNU GPL v3.0
Author: Jonny Saunders
Author-email: sneakers-the-rat@protonmail.com
Requires-Python: >=3.9,<4.0
Classifier: License :: Other/Proprietary License
Classifier: Programming Language :: Python :: 3
Classifier: Programming Language :: Python :: 3.9
Classifier: Programming Language :: Python :: 3.10
Classifier: Programming Language :: Python :: 3.11
Provides-Extra: docs
Requires-Dist: linkml-runtime (>=1.1.24,<2.0.0)
Requires-Dist: pydantic (>=2.5.3,<3.0.0)
